compiled_jss/CPEnv.py
compiled_jss/instances/dmu01.txt
compiled_jss/instances/dmu02.txt
compiled_jss/instances/dmu03.txt
compiled_jss/instances/dmu04.txt
compiled_jss/instances/dmu05.txt
compiled_jss/instances/dmu06.txt
compiled_jss/instances/dmu07.txt
compiled_jss/instances/dmu08.txt
compiled_jss/instances/dmu09.txt
compiled_jss/instances/dmu10.txt
compiled_jss/instances/dmu11.txt
compiled_jss/instances/dmu12.txt
compiled_jss/instances/dmu13.txt
compiled_jss/instances/dmu14.txt
compiled_jss/instances/dmu15.txt
compiled_jss/instances/dmu16.txt
compiled_jss/instances/dmu17.txt
compiled_jss/instances/dmu18.txt
compiled_jss/instances/dmu19.txt
compiled_jss/instances/dmu20.txt
compiled_jss/instances/dmu21.txt
compiled_jss/instances/dmu22.txt
compiled_jss/instances/dmu23.txt
compiled_jss/instances/dmu24.txt
compiled_jss/instances/dmu25.txt
compiled_jss/instances/dmu26.txt
compiled_jss/instances/dmu27.txt
compiled_jss/instances/dmu28.txt
compiled_jss/instances/dmu29.txt
compiled_jss/instances/dmu30.txt
compiled_jss/instances/dmu31.txt
compiled_jss/instances/dmu32.txt
compiled_jss/instances/dmu33.txt
compiled_jss/instances/dmu34.txt
compiled_jss/instances/dmu35.txt
compiled_jss/instances/dmu36.txt
compiled_jss/instances/dmu37.txt
compiled_jss/instances/dmu38.txt
compiled_jss/instances/dmu39.txt
compiled_jss/instances/dmu40.txt
compiled_jss/instances/dmu41.txt
compiled_jss/instances/dmu42.txt
compiled_jss/instances/dmu43.txt
compiled_jss/instances/dmu44.txt
compiled_jss/instances/dmu45.txt
compiled_jss/instances/dmu46.txt
compiled_jss/instances/dmu47.txt
compiled_jss/instances/dmu48.txt
compiled_jss/instances/dmu49.txt
compiled_jss/instances/dmu50.txt
compiled_jss/instances/dmu51.txt
compiled_jss/instances/dmu52.txt
compiled_jss/instances/dmu53.txt
compiled_jss/instances/dmu54.txt
compiled_jss/instances/dmu55.txt
compiled_jss/instances/dmu56.txt
compiled_jss/instances/dmu57.txt
compiled_jss/instances/dmu58.txt
compiled_jss/instances/dmu59.txt
job_shop_cp_env-1.0.0.dist-info/LICENSE
job_shop_cp_env-1.0.0.dist-info/METADATA
job_shop_cp_env-1.0.0.dist-info/WHEEL
job_shop_cp_env-1.0.0.dist-info/top_level.txt
job_shop_cp_env-1.0.0.dist-info/RECORD
