Metadata-Version: 2.1
Name: job-shop-cp-env
Version: 1.0.0
Summary: An optimized RL approach to learn and simulate the Job-Shop Scheduling problem using Constraint Programming
Home-page: https://github.com/ingambe
Author: Pierre Tassel
Author-email: Pierre Tassel <pierre.tassel@outlook.fr>
Project-URL: Homepage, https://github.com/ingambe/JobShopCPEnv
Project-URL: Bug Tracker, https://github.com/ingambe/JobShopCPEnv/issues
Classifier: Programming Language :: Python :: 3
Classifier: License :: OSI Approved :: MIT License
Classifier: Operating System :: OS Independent
Requires-Python: >=3.8
License-File: LICENSE
Requires-Dist: mypy
Requires-Dist: gym
Requires-Dist: numpy
Requires-Dist: matplotlib
Requires-Dist: docplex
Requires-Dist: cloudpickle
